sample_project/__init__.py
sample_project/sample.py
sample_pypi_mitzlibrary-0.0.1.dist-info/METADATA
sample_pypi_mitzlibrary-0.0.1.dist-info/WHEEL
sample_pypi_mitzlibrary-0.0.1.dist-info/top_level.txt
sample_pypi_mitzlibrary-0.0.1.dist-info/RECORD
