Metadata-Version: 2.1
Name: sample-pypi-mitzlibrary
Version: 0.0.1
Summary: A sample Python library to demonstrate PyPI publishing
Home-page: https://github.com/MithunChandrasekar/example-pkg-mitz
Author: Mithun Chandrasekar
Author-email: mithunxchandrasekar1@gmail.com
Classifier: Programming Language :: Python :: 3
Classifier: License :: OSI Approved :: MIT License
Classifier: Operating System :: OS Independent
Requires-Python: >=3.6
